gymize/__init__.py
gymize/bridge.py
gymize/channel.py
gymize/lanch.py
gymize/render.py
gymize/signaling.py
gymize/space.py
gymize/envs/__init__.py
gymize/envs/unity_aec_env.py
gymize/envs/unity_gym_env.py
gymize/envs/unity_parallel_env.py
gymize/proto/__init__.py
gymize/proto/channel_pb2.py
gymize/proto/gymize_pb2.py
gymize/proto/locator_pb2.py
gymize/proto/render_pb2.py
gymize/proto/signaling_pb2.py
gymize/proto/space_pb2.py
gymize-0.0.3.dist-info/METADATA
gymize-0.0.3.dist-info/WHEEL
gymize-0.0.3.dist-info/entry_points.txt
gymize-0.0.3.dist-info/RECORD
