Metadata-Version: 2.1
Name: gymize
Version: 0.0.3
Summary: Unity and Python Reinforcement and Imitation Learning with Gymnasium and PettingZoo API.
Project-URL: Homepage, https://github.com/timcsy/gymize
Project-URL: Bug Tracker, https://github.com/timcsy/gymize/issues
Author-email: timcsy <timocsy@yahoo.com.tw>
Classifier: License :: OSI Approved :: MIT License
Classifier: Operating System :: OS Independent
Classifier: Programming Language :: Python :: 3
Requires-Python: >=3.8
Requires-Dist: gymnasium>=0.28
Requires-Dist: pettingzoo>=1.23
Requires-Dist: protobuf>=3.18
Requires-Dist: websockets==10.1
